{"sdg_goal":"11","indicator_number":11.8,"graph_title":"Naherholungsfl\u00e4che","indicator_sort_order":"11-08-01","data_non_statistical":false,"graph_type":"line","computation_units":"absolut","data_start_values":[{"field":"Region","value":"Enzkreis"},{"field":"Region","value":"Land BW"}],"national_geographical_coverage":"Land BW","computation_definitions":"Anteil der Sport-, Freizeit-, und Erholungsfl\u00e4chen an der Bodenfl\u00e4che insgesamt (in ha und %)","SOURCE_TYPE":"Statistisches Landesamt BW","source_earliest_available_1":2008,"source_periodicity_1":"Einjahresintervalle","language":"de","published":true,"reporting_status":"complete","page_content":"\nErholungsfl\u00e4chen umfassen unbebaute Fl\u00e4chen, die \u00fcberwiegend dem Sport, der Erholung oder dazu dienen, Tiere oder Pflanzen zu zeigen. Zu diesen Fl\u00e4chen geh\u00f6ren u. a. Gr\u00fcnanlagen, Parks, Schreberg\u00e4rten sowie Sportfl\u00e4chen und Campingpl\u00e4tze.\nSport-, Freizeit-, und Erholungsfl\u00e4chen erf\u00fcllen wichtige soziale, \u00f6kologische und \u00f6konomische Funktionen. So haben Erholungsfl\u00e4chen einen hohen Freizeitwert, k\u00f6nnen Stress reduzieren und als Treffpunkt verschiedener sozialer Milieus dienen. Erholungsfl\u00e4chen haben jedoch auch einen hohen \u00f6kologischen Mehrwert, da sie klimaregulierend und luftfilternd wirken.","national_metadata_updated_date":"2022-11-16","national_data_updated_date":"2022-11-16","national_metadata_update_url_text":"2022-11-16: see changes on GitHub","national_metadata_update_url":"https://github.com/tt053626/sdg-enz-staging-data/commit/22658b46ba5ff34270cf7b24fc93d1c5d795c085","national_data_update_url_text":"2022-11-16: see changes on GitHub","national_data_update_url":"https://github.com/tt053626/sdg-enz-staging-data/commit/ed5651808a5c753e0eeb1306952f6c5ae70f832b","indicator":"11.8","target_id":"11.8","indicator_name":"Naherholungsfl\u00e4che"}